eki/__init__.py
eki/__main__.py
eki/login.py
eki/mal.py
eki/tracker.py
eki/video_extensions.py
eki-0.0.6.dist-info/METADATA
eki-0.0.6.dist-info/WHEEL
eki-0.0.6.dist-info/entry_points.txt
eki-0.0.6.dist-info/top_level.txt
eki-0.0.6.dist-info/RECORD
