Metadata-Version: 2.1
Name: eki
Version: 0.0.6
Summary: MyAnimeList tracker for local anime files.
Home-page: https://github.com/laxyapahuja/eki
Author: Laxya Pahuja
Author-email: laxya.pahuja8@gmail.com
License: UNKNOWN
Project-URL: Documentation, https://github.com/laxyapahuja/eki/README.md
Project-URL: Source, https://github.com/laxyapahuja/eki
Platform: UNKNOWN
Classifier: Programming Language :: Python :: 3
Classifier: License :: OSI Approved :: MIT License
Classifier: Operating System :: OS Independent
Requires-Python: >=3.6
Requires-Dist: malupdate
Requires-Dist: pywin32
Requires-Dist: pymediainfo
